agile_conf
