Metadata-Version: 1.1
Name: agile-conf
Version: 1.0.3
Summary: A config files (in [YAML](http://yaml.org) format) and template engine ([Jinja2](http://jinja.pocoo.org)) based configuration compile / management tool to make DevOp tasks
Home-page: https://github.com/tly1980/agile_conf
Author: Tom Tang
Author-email: tly1980@gmail.com
License: BSD
Platform: any
Classifier: Development Status :: 2 - Pre-Alpha
Classifier: Environment :: Web Environment
Classifier: Intended Audience :: Developers
Classifier: License :: OSI Approved :: BSD License
Classifier: Operating System :: OS Independent
Classifier: Programming Language :: Python
Classifier: Topic :: Software Development :: Build Tools
Classifier: Topic :: Software Development :: Code Generators
